{
  "date": "2026-04-22",
  "generated_at": "21:21 IST",
  "market_open": true,
  "regime": "BULLISH",
  "regime_desc": "Uptrend \u2014 full position sizes",
  "nifty_rsi": 59.6,
  "nifty_adx": 24.4,
  "vix": 17.5,
  "vix_action": "normal",
  "floor_hit": false,
  "consec_losses": 1,
  "size_multiplier": 1.0,
  "picks": [
    {
      "ticker": "HEROMOTOCO.NS",
      "name": "HEROMOTOCO",
      "sector": "AUTO",
      "entry": 5259.0,
      "sl": 4942.88,
      "target": 5733.18,
      "partial_tgt": 5575.12,
      "rr": 1.5,
      "qty": 18,
      "capital": 94662.0,
      "atr": 158.06,
      "setup_type": "RSI_DIVERGENCE",
      "setup_display": "RSI divergence forming",
      "conf_score": 5,
      "conf_label": "BUY",
      "hold_days": 8,
      "ev_pct": 2.25,
      "p_win": 55.0,
      "rvol": 0.52,
      "weekly_info": {
        "setup": "RSI_DIVERGENCE",
        "weekly_rsi": 47.9,
        "rsi_divergence": 2.7,
        "weekly_score": 3
      },
      "reason": "RSI divergence \u2014 price at low, RSI 49 above recent low",
      "already_open": false,
      "vix_reduced": false,
      "sector_uptrend": true
    },
    {
      "ticker": "RELIANCE.NS",
      "name": "RELIANCE",
      "sector": "ENERGY",
      "entry": 1353.3,
      "sl": 1294.31,
      "target": 1441.79,
      "partial_tgt": 1412.29,
      "rr": 1.5,
      "qty": 101,
      "capital": 136683.0,
      "atr": 29.5,
      "setup_type": "RSI_DIVERGENCE",
      "setup_display": "RSI divergence forming",
      "conf_score": 5,
      "conf_label": "BUY",
      "hold_days": 8,
      "ev_pct": 1.63,
      "p_win": 55.0,
      "rvol": 1.28,
      "weekly_info": {
        "setup": "RSI_DIVERGENCE",
        "weekly_rsi": 42.4,
        "rsi_divergence": 2.7,
        "weekly_score": 3
      },
      "reason": "RSI divergence \u2014 price at low, RSI 47 above recent low",
      "already_open": true,
      "vix_reduced": false,
      "sector_uptrend": true
    }
  ],
  "error": null
}